src/SPBRAM.v
//
// verilog that synthesizes to Single Port RAM
//

`default_nettype none
`define DBG
`define INFO

module SPBRAM #(
    parameter DATA_FILE = "",
    parameter ADDRESS_BITWIDTH = 16,
    parameter DATA_BITWIDTH = 32
) (
    input wire clk,
    input wire write_enable,
    input wire [ADDRESS_BITWIDTH-1:0] address,
    output reg [DATA_BITWIDTH-1:0] data_out,
    input wire [DATA_BITWIDTH-1:0] data_in
);

  initial begin
    if (DATA_FILE != "") begin
      $readmemh(DATA_FILE, data, 0, 2 ** ADDRESS_BITWIDTH - 1);
    end
  end

  reg [DATA_BITWIDTH-1:0] data[2**ADDRESS_BITWIDTH-1:0];

  always @(posedge clk) begin
    // $display("RAM: write_enable: %d  address: %h  data_in: %h", write_enable, address, data_in);
    if (write_enable == 1) begin
      data[address] <= data_in;
    end
    data_out <= data[address];
  end

endmodule

`undef DBG
`undef INFO
`default_nettype wire

src/Cache.v
`default_nettype none

module Cache #(
    parameter LINE_IX_BITWIDTH = 8
) (
    input wire clk,
    input wire rst_n,
    input wire [31:0] address,
    output reg [31:0] data_out,
    output reg data_out_valid,
    input wire [31:0] data_in,
    input wire write_enable
);
  // 4 column cache line
  localparam ZEROS_BITWIDTH = 2;
  localparam COLUMN_IX_BITWIDTH = 2;  // 4 SPBRAMs
  localparam LINE_COUNT = 2 ** LINE_IX_BITWIDTH;
  localparam TAG_BITWIDTH = 32 - LINE_IX_BITWIDTH - COLUMN_IX_BITWIDTH - ZEROS_BITWIDTH;
  localparam LINE_VALID_BIT = TAG_BITWIDTH;
  localparam LINE_DIRTY_BIT = TAG_BITWIDTH + 1;

  wire [COLUMN_IX_BITWIDTH-1:0] column_ix = address[COLUMN_IX_BITWIDTH+ZEROS_BITWIDTH-1-:COLUMN_IX_BITWIDTH];
  wire [LINE_IX_BITWIDTH-1:0] line_ix =  address[LINE_IX_BITWIDTH+COLUMN_IX_BITWIDTH+ZEROS_BITWIDTH-1-:LINE_IX_BITWIDTH];
  wire [TAG_BITWIDTH-1:0] line_tag_in = address[TAG_BITWIDTH+LINE_IX_BITWIDTH+COLUMN_IX_BITWIDTH+ZEROS_BITWIDTH-1-:TAG_BITWIDTH];

  SPBRAM #(
      .ADDRESS_BITWIDTH(LINE_IX_BITWIDTH)
  ) tag (
      .clk(clk),
      .write_enable(write_enable_tag),
      .address(line_ix),
      .data_in({{(30 - TAG_BITWIDTH) {1'b0}}, 1'b0, 1'b1, line_tag_in}),
      // note: 30 because 2 bits are used for 'valid' and 'dirty' flags
      .data_out(line_tag_and_valid_dirty)
  );
  wire [31:0] line_tag_and_valid_dirty;
  wire line_valid = line_tag_and_valid_dirty[LINE_VALID_BIT];
  wire line_dirty = line_tag_and_valid_dirty[LINE_DIRTY_BIT];
  wire [TAG_BITWIDTH-1:0] line_tag = line_tag_and_valid_dirty[TAG_BITWIDTH-1:0];

  SPBRAM #(
      .ADDRESS_BITWIDTH(LINE_IX_BITWIDTH)
  ) data0 (
      .clk(clk),
      .write_enable(write_enable_0),
      .address(line_ix),
      .data_in(data_in),
      .data_out(data0_out)
  );

  SPBRAM #(
      .ADDRESS_BITWIDTH(LINE_IX_BITWIDTH)
  ) data1 (
      .clk(clk),
      .write_enable(write_enable_1),
      .address(line_ix),
      .data_in(data_in),
      .data_out(data1_out)
  );

  SPBRAM #(
      .ADDRESS_BITWIDTH(LINE_IX_BITWIDTH)
  ) data2 (
      .clk(clk),
      .write_enable(write_enable_2),
      .address(line_ix),
      .data_in(data_in),
      .data_out(data2_out)
  );

  SPBRAM #(
      .ADDRESS_BITWIDTH(LINE_IX_BITWIDTH)
  ) data3 (
      .clk(clk),
      .write_enable(write_enable_3),
      .address(line_ix),
      .data_in(data_in),
      .data_out(data3_out)
  );

  wire [31:0] data0_out;
  wire [31:0] data1_out;
  wire [31:0] data2_out;
  wire [31:0] data3_out;
  reg write_enable_tag;
  reg write_enable_0;
  reg write_enable_1;
  reg write_enable_2;
  reg write_enable_3;

  always @(*) begin
    case (column_ix)
      0: data_out = data0_out;
      1: data_out = data1_out;
      2: data_out = data2_out;
      3: data_out = data3_out;
      default: data_out = 32'hffff_ffff;
    endcase
  end

  always @(*) begin
    // check that the upper bits of the address are the same and cache line valid
    data_out_valid = line_valid && line_tag_in == line_tag;
  end

  always @(*) begin
    write_enable_tag = 0;
    write_enable_0   = 0;
    write_enable_1   = 0;
    write_enable_2   = 0;
    write_enable_3   = 0;
    if (write_enable) begin
      write_enable_tag = 1;
      case (column_ix)
        0: write_enable_0 = 1;
        1: write_enable_1 = 1;
        2: write_enable_2 = 1;
        3: write_enable_3 = 1;
      endcase
    end
  end

  always @(posedge clk) begin

  end

  reg [3:0] state;

  always @(posedge clk) begin
    case (state)
      default: ;

    endcase
  end

endmodule

`default_nettype wire

qa/1/TestBench.v
`timescale 1ns / 1ps `default_nettype none

module TestBench;

  Cache #(
      .LINE_IX_BITWIDTH(10)
  ) cache (
      .clk(clk),
      .rst_n(sys_rst_n),
      .address(address),
      .data_out(data_out),
      .data_out_valid(data_out_valid),
      .data_in(data_in),
      .write_enable(write_enable)
  );

  reg clk = 1;
  reg sys_rst_n = 0;
  reg write_enable;
  reg [31:0] address;
  reg [31:0] data_in;
  wire [31:0] data_out;
  wire data_out_valid;

  localparam clk_tk = 4;
  always #(clk_tk / 2) clk = ~clk;

  integer i;

  initial begin
    $dumpfile("log.vcd");
    $dumpvars(0, TestBench);

    // clear the cache
    for (i = 0; i < 2 ** 10; i = i + 1) begin
      cache.tag.data[i]   = 0;
      cache.data0.data[i] = 0;
      cache.data1.data[i] = 0;
      cache.data2.data[i] = 0;
      cache.data3.data[i] = 0;
    end

    #clk_tk;
    sys_rst_n <= 1;
    #clk_tk;

    // write
    address <= 4;
    data_in <= 32'habcd_ef12;
    write_enable <= 1;
    #clk_tk;

    // // dump the cache
    // for (i = 0; i < 8; i = i + 1) begin
    //   $display("1). %h : %h  %h  %h  %h", cache.tag.data[i], cache.data0.data[i],
    //            cache.data1.data[i], cache.data2.data[i], cache.data3.data[i]);
    // end

    // write
    address <= 8;
    data_in <= 32'habcd_1234;
    write_enable <= 1;
    #clk_tk;

    // one cycle delay. value for address 4
    if (data_out == 32'habcd_ef12 && data_out_valid) $display("Test 1 passed");
    else $display("Test 1 FAILED");

    // read; cache hit
    address <= 4;
    write_enable <= 0;
    #clk_tk;

    // read; cache hit
    address <= 8;
    write_enable <= 0;
    #clk_tk;

    // read; not valid
    address <= 16;
    write_enable <= 0;
    #clk_tk;

    if (data_out == 32'habcd_1234 && data_out_valid) $display("Test 2 passed");
    else $display("Test 2 FAILED");

    if (!data_out_valid) $display("Test 3 passed");
    else $display("Test 3 FAILED");

    #clk_tk;
    #clk_tk;
    #clk_tk;
    #clk_tk;

    $finish;
  end

endmodule

`default_nettype wire

qa/1/log.vcd
$date
	Wed Jun  5 14:25:18 2024
$end
$version
	Icarus Verilog
$end
$timescale
	1ps
$end
$scope module TestBench $end
$var wire 1 ! data_out_valid $end
$var wire 32 " data_out [31:0] $end
$var parameter 32 # clk_tk $end
$var reg 32 $ address [31:0] $end
$var reg 1 % clk $end
$var reg 32 & data_in [31:0] $end
$var reg 1 ' sys_rst_n $end
$var reg 1 ( write_enable $end
$var integer 32 ) i [31:0] $end
$scope module cache $end
$var wire 32 * address [31:0] $end
$var wire 1 % clk $end
$var wire 32 + data_in [31:0] $end
$var wire 1 ' rst_n $end
$var wire 1 ( write_enable $end
$var wire 1 , line_valid $end
$var wire 18 - line_tag_in [17:0] $end
$var wire 32 . line_tag_and_valid_dirty [31:0] $end
$var wire 18 / line_tag [17:0] $end
$var wire 10 0 line_ix [9:0] $end
$var wire 1 1 line_dirty $end
$var wire 32 2 data3_out [31:0] $end
$var wire 32 3 data2_out [31:0] $end
$var wire 32 4 data1_out [31:0] $end
$var wire 32 5 data0_out [31:0] $end
$var wire 2 6 column_ix [1:0] $end
$var parameter 32 7 COLUMN_IX_BITWIDTH $end
$var parameter 32 8 LINE_COUNT $end
$var parameter 36 9 LINE_DIRTY_BIT $end
$var parameter 32 : LINE_IX_BITWIDTH $end
$var parameter 35 ; LINE_VALID_BIT $end
$var parameter 35 < TAG_BITWIDTH $end
$var parameter 32 = ZEROS_BITWIDTH $end
$var reg 32 > data_out [31:0] $end
$var reg 1 ! data_out_valid $end
$var reg 4 ? state [3:0] $end
$var reg 1 @ write_enable_0 $end
$var reg 1 A write_enable_1 $end
$var reg 1 B write_enable_2 $end
$var reg 1 C write_enable_3 $end
$var reg 1 D write_enable_tag $end
$scope module data0 $end
$var wire 10 E address [9:0] $end
$var wire 1 % clk $end
$var wire 32 F data_in [31:0] $end
$var wire 1 @ write_enable $end
$var parameter 32 G ADDRESS_BITWIDTH $end
$var parameter 32 H DATA_BITWIDTH $end
$var parameter 0 I DATA_FILE $end
$var reg 32 J data_out [31:0] $end
$upscope $end
$scope module data1 $end
$var wire 10 K address [9:0] $end
$var wire 1 % clk $end
$var wire 32 L data_in [31:0] $end
$var wire 1 A write_enable $end
$var parameter 32 M ADDRESS_BITWIDTH $end
$var parameter 32 N DATA_BITWIDTH $end
$var parameter 0 O DATA_FILE $end
$var reg 32 P data_out [31:0] $end
$upscope $end
$scope module data2 $end
$var wire 10 Q address [9:0] $end
$var wire 1 % clk $end
$var wire 32 R data_in [31:0] $end
$var wire 1 B write_enable $end
$var parameter 32 S ADDRESS_BITWIDTH $end
$var parameter 32 T DATA_BITWIDTH $end
$var parameter 0 U DATA_FILE $end
$var reg 32 V data_out [31:0] $end
$upscope $end
$scope module data3 $end
$var wire 10 W address [9:0] $end
$var wire 1 % clk $end
$var wire 32 X data_in [31:0] $end
$var wire 1 C write_enable $end
$var parameter 32 Y ADDRESS_BITWIDTH $end
$var parameter 32 Z DATA_BITWIDTH $end
$var parameter 0 [ DATA_FILE $end
$var reg 32 \ data_out [31:0] $end
$upscope $end
$scope module tag $end
$var wire 10 ] address [9:0] $end
$var wire 1 % clk $end
$var wire 32 ^ data_in [31:0] $end
$var wire 1 D write_enable $end
$var parameter 32 _ ADDRESS_BITWIDTH $end
$var parameter 32 ` DATA_BITWIDTH $end
$var parameter 0 a DATA_FILE $end
$var reg 32 b data_out [31:0] $end
$upscope $end
$upscope $end
$upscope $end
$enddefinitions $end
$comment Show the parameter values. $end
$dumpall
b a
b100000 `
b1010 _
b [
b100000 Z
b1010 Y
b U
b100000 T
b1010 S
b O
b100000 N
b1010 M
b I
b100000 H
b1010 G
b10 =
b10010 <
b10010 ;
b1010 :
b10011 9
b10000000000 8
b10 7
b100 #
$end
#0
$dumpvars
bx b
b1xxxxxxxxxxxxxxxxxx ^
bx ]
bx \
bx X
bx W
bx V
bx R
bx Q
bx P
bx L
bx K
bx J
bx F
bx E
xD
xC
xB
xA
x@
bx ?
bx >
bx 6
bx 5
bx 4
bx 3
bx 2
x1
bx 0
bx /
bx .
bx -
x,
bx +
bx *
b10000000000 )
x(
0'
bx &
1%
bx $
bx "
x!
$end
#2000
0%
#4000
1'
1%
#6000
0%
#8000
0C
0B
1A
0@
1D
b1 6
b0 0
b0 E
b0 K
b0 Q
b0 W
b0 ]
b1000000000000000000 ^
b0 -
1(
b10101011110011011110111100010010 &
b10101011110011011110111100010010 +
b10101011110011011110111100010010 F
b10101011110011011110111100010010 L
b10101011110011011110111100010010 R
b10101011110011011110111100010010 X
b100 $
b100 *
1%
#10000
0%
#12000
0!
1B
0A
1D
b0 "
b0 >
b0 /
01
0,
b10 6
b0 2
b0 \
b0 3
b0 V
b0 4
b0 P
b0 5
b0 J
b0 .
b0 b
b10101011110011010001001000110100 &
b10101011110011010001001000110100 +
b10101011110011010001001000110100 F
b10101011110011010001001000110100 L
b10101011110011010001001000110100 R
b10101011110011010001001000110100 X
b1000 $
b1000 *
1%
#14000
0%
#16000
1!
1,
b10101011110011011110111100010010 "
b10101011110011011110111100010010 >
0B
0D
b1 6
b1000000000000000000 .
b1000000000000000000 b
b10101011110011011110111100010010 4
b10101011110011011110111100010010 P
0(
b100 $
b100 *
1%
#18000
0%
#20000
b10101011110011010001001000110100 "
b10101011110011010001001000110100 >
b10 6
b10101011110011010001001000110100 3
b10101011110011010001001000110100 V
b1000 $
b1000 *
1%
#22000
0%
#24000
b0 "
b0 >
b0 6
b1 0
b1 E
b1 K
b1 Q
b1 W
b1 ]
b10000 $
b10000 *
1%
#26000
0%
#28000
0!
0,
b0 3
b0 V
b0 4
b0 P
b0 .
b0 b
1%
